xeauth/__init__.py
xeauth/admin.py
xeauth/cli.py
xeauth/github.py
xeauth/integrations/panel.py
xeauth/settings.py
xeauth/user.py
xeauth/utils.py
xeauth-0.2.3.dist-info/WHEEL
xeauth-0.2.3.dist-info/METADATA
xeauth-0.2.3.dist-info/entry_points.txt
xeauth-0.2.3.dist-info/LICENSE
xeauth-0.2.3.dist-info/RECORD
