Metadata-Version: 2.1
Name: xeauth
Version: 0.2.3
Summary: Top-level package for xeauth.
Home-page: https://github.com/jmosbacher/xeauth
License: MIT
Author: Yossi Mosbacher
Author-email: joe.mosbacher@gmail.com
Requires-Python: >=3.7,<4
Classifier: Development Status :: 2 - Pre-Alpha
Classifier: Intended Audience :: Developers
Classifier: License :: OSI Approved :: MIT License
Classifier: Natural Language :: English
Classifier: Programming Language :: Python :: 3
Classifier: Programming Language :: Python :: 3.7
Classifier: Programming Language :: Python :: 3.8
Classifier: Programming Language :: Python :: 3.9
Classifier: Programming Language :: Python :: 3.10
Classifier: Programming Language :: Python :: 3.11
Classifier: Programming Language :: Python :: 3.8
Requires-Dist: appdirs (>=1.4.4,<2.0.0)
Requires-Dist: click
Requires-Dist: gnupg (>=2.3.1,<3.0.0)
Requires-Dist: httpx (>=0.19,<0.25)
Requires-Dist: param (>=1.12.0,<2.0.0)
Requires-Dist: rich (>=13.1.0,<14.0.0)
